grievance_social_protection/__init__.py
grievance_social_protection/admin.py
grievance_social_protection/apps.py
grievance_social_protection/documents.py
grievance_social_protection/gql_mutations.py
grievance_social_protection/gql_queries.py
grievance_social_protection/models.py
grievance_social_protection/schema.py
grievance_social_protection/services.py
grievance_social_protection/urls.py
grievance_social_protection/util.py
grievance_social_protection/validations.py
grievance_social_protection/views.py
grievance_social_protection/migrations/0001_initial.py
grievance_social_protection/migrations/0002_grievancemutation.py
grievance_social_protection/migrations/0003_auto_20221130_1620.py
grievance_social_protection/migrations/0004_auto_20230425_1638.py
grievance_social_protection/migrations/0005_auto_20230703_1349.py
grievance_social_protection/migrations/0006_add_admin_rights.py
grievance_social_protection/migrations/0007_auto_20230811_1314.py
grievance_social_protection/migrations/0008_auto_20240414_2138.py
grievance_social_protection/migrations/0009_comment_historicalcomment_historicalticket_ticket_ticketmutation.py
grievance_social_protection/migrations/0010_auto_20240417_1050.py
grievance_social_protection/migrations/0011_auto_20240418_1130.py
grievance_social_protection/migrations/0012_auto_20240418_1137.py
grievance_social_protection/migrations/0013_auto_20240422_2108.py
grievance_social_protection/migrations/0014_add_grievance_social_protection_rights_to_admin.py
grievance_social_protection/migrations/0015_auto_20240423_1318.py
grievance_social_protection/migrations/0016_auto_20240423_1324.py
grievance_social_protection/migrations/0017_auto_20240430_1523.py
grievance_social_protection/migrations/0018_alter_comment_user_created_and_more.py
grievance_social_protection/migrations/__init__.py
grievance_social_protection/tests/__init__.py
grievance_social_protection/tests/data.py
grievance_social_protection/tests/gql_payloads.py
openimis_be_grievance_social_protection-1.2.0.dist-info/licenses/LICENSE.md
openimis_be_grievance_social_protection-1.2.0.dist-info/METADATA
openimis_be_grievance_social_protection-1.2.0.dist-info/WHEEL
openimis_be_grievance_social_protection-1.2.0.dist-info/top_level.txt
openimis_be_grievance_social_protection-1.2.0.dist-info/RECORD
